DESIGN.rst
MANIFEST.in
README.rst
TODO.rst
requirements.txt
setup.py
carbontube/__init__.py
carbontube/clients.py
carbontube/models.py
carbontube/util.py
carbontube/version.py
carbontube.egg-info/PKG-INFO
carbontube.egg-info/SOURCES.txt
carbontube.egg-info/dependency_links.txt
carbontube.egg-info/entry_points.txt
carbontube.egg-info/not-zip-safe
carbontube.egg-info/requires.txt
carbontube.egg-info/top_level.txt
carbontube/console/__init__.py
carbontube/console/base.py
carbontube/console/clients.py
carbontube/console/main.py
carbontube/console/servers.py
carbontube/console/web.py
carbontube/console/parsers/__init__.py
carbontube/console/parsers/bundle.py
carbontube/console/parsers/enqueue.py
carbontube/console/parsers/forwarder.py
carbontube/console/parsers/phase.py
carbontube/console/parsers/pipeline.py
carbontube/console/parsers/streamer.py
carbontube/console/parsers/web.py
carbontube/extensions/__init__.py
carbontube/extensions/meta.py
carbontube/extensions/registry.py
carbontube/servers/__init__.py
carbontube/servers/phases.py
carbontube/servers/pipelines.py
carbontube/storage/__init__.py
carbontube/storage/__init__.pyc
carbontube/storage/base.py
carbontube/storage/base.pyc
carbontube/storage/inmemory.py
carbontube/storage/inmemory.pyc
carbontube/storage/pyredis.py
carbontube/storage/pyredis.pyc
carbontube/storage/redis-lua-scripts/consume-by-type.lua
carbontube/storage/redis-lua-scripts/consume.lua
carbontube/storage/redis-lua-scripts/enqueue.lua
carbontube/storage/redis-lua-scripts/list-pending-jobs-by-type.lua
carbontube/storage/redis-lua-scripts/list-pending-jobs.lua
carbontube/web/.gitignore
carbontube/web/0c8594f565ab93de07dc647481099c6c.jpg
carbontube/web/448c34a56d699c29117adc64c43affeb.woff2
carbontube/web/89889688147bd7575d6327160d64e760.svg
carbontube/web/Makefile
carbontube/web/__init__.py
carbontube/web/__init__.pyc
carbontube/web/e18bbf611f2a2e43afc071aa2f4e1512.ttf
carbontube/web/f4769f9bdb7466be65088239c12046d1.eot
carbontube/web/fa2772327f55d8198301fdb8bcfc8158.woff
carbontube/web/favicon.ico
carbontube/web/package-lock.json
carbontube/web/package.json
carbontube/web/requirements.txt
carbontube/web/webpack.config.js
carbontube/web/dist/carbontube-webapp.js
