Metadata-Version: 1.0
Name: carbontube
Version: 0.1.1
Summary: CarbonTube is a ZeroMQ-based distributed pipeline framework.
Home-page: https://github.com/gabrielfalcao/carbontube
Author: Gabriel Falcao
Author-email: gabriel@nacaolivre.org
License: UNKNOWN
Platform: UNKNOWN
